MANIFEST.in
README.rst
setup.py
certidude/__init__.py
certidude/auth.py
certidude/authority.py
certidude/cli.py
certidude/common.py
certidude/config.py
certidude/constants.py
certidude/decorators.py
certidude/errors.py
certidude/firewall.py
certidude/helpers.py
certidude/mailer.py
certidude/mysqllog.py
certidude/push.py
certidude/relational.py
certidude/signer.py
certidude/user.py
certidude/wrappers.py
certidude/wsgi.py
certidude.egg-info/PKG-INFO
certidude.egg-info/SOURCES.txt
certidude.egg-info/dependency_links.txt
certidude.egg-info/pbr.json
certidude.egg-info/requires.txt
certidude.egg-info/top_level.txt
certidude/api/__init__.py
certidude/api/cfg.py
certidude/api/lease.py
certidude/api/log.py
certidude/api/request.py
certidude/api/revoked.py
certidude/api/signed.py
certidude/api/tag.py
certidude/api/whois.py
certidude/sql/mysql/log_insert_entry.sql
certidude/sql/mysql/log_tables.sql
certidude/sql/mysql/tag_insert.sql
certidude/sql/mysql/tag_tables.sql
certidude/sql/sqlite/log_insert_entry.sql
certidude/sql/sqlite/log_tables.sql
certidude/sql/sqlite/tag_delete.sql
certidude/sql/sqlite/tag_insert.sql
certidude/sql/sqlite/tag_list.sql
certidude/sql/sqlite/tag_tables.sql
certidude/sql/sqlite/tag_update.sql
certidude/static/index.html
certidude/static/css/style.css
certidude/static/fonts/gentium-basic.woff2
certidude/static/fonts/pt-sans.woff2
certidude/static/fonts/ubuntu-mono.woff2
certidude/static/img/iconmonstr-barcode-4.svg
certidude/static/img/iconmonstr-calendar-6.svg
certidude/static/img/iconmonstr-certificate-15.svg
certidude/static/img/iconmonstr-compass-7.svg
certidude/static/img/iconmonstr-download-12.svg
certidude/static/img/iconmonstr-email-2.svg
certidude/static/img/iconmonstr-error-4.svg
certidude/static/img/iconmonstr-flag-3.svg
certidude/static/img/iconmonstr-home-7.svg
certidude/static/img/iconmonstr-info-8.svg
certidude/static/img/iconmonstr-key-3.svg
certidude/static/img/iconmonstr-magnifier-4.svg
certidude/static/img/iconmonstr-mobile-phone-7.svg
certidude/static/img/iconmonstr-pen-14.svg
certidude/static/img/iconmonstr-tag-3.svg
certidude/static/img/iconmonstr-user-5.svg
certidude/static/img/iconmonstr-warning-8.svg
