Metadata-Version: 1.1
Name: certidude
Version: 0.1.21
Summary: Certidude is a novel X.509 Certificate Authority management tool aiming to support PKCS#11 and in far future WebCrypto.
Home-page: http://github.com/laurivosandi/certidude
Author: Lauri Võsandi
Author-email: lauri.vosandi@gmail.com
License: MIT
Keywords: falcon http jinja2 x509 pkcs11 webcrypto
Platform: UNKNOWN
Classifier: Development Status :: 4 - Beta
Classifier: Environment :: Console
Classifier: Intended Audience :: Developers
Classifier: Intended Audience :: System Administrators
Classifier: License :: Freely Distributable
Classifier: License :: OSI Approved :: MIT License
Classifier: Natural Language :: English
Classifier: Operating System :: POSIX :: Linux
Classifier: Programming Language :: Python
Classifier: Programming Language :: Python :: 3 :: Only
